parsenvy/__init__.py
parsenvy/parsenvy.py
parsenvy/py.typed
parsenvy-3.0.3.dist-info/METADATA
parsenvy-3.0.3.dist-info/WHEEL
parsenvy-3.0.3.dist-info/licenses/LICENSE
parsenvy-3.0.3.dist-info/RECORD
